{
  "task": "enwik8",
  "arch": "transformer",
  "args": {
    "arch": "transformer",
    "short_conv": true,
    "d_model": 128,
    "n_layers": 2,
    "n_heads": 4,
    "ffn_mult": 2.0,
    "seq_len": 256,
    "batch": 32,
    "steps": 1500,
    "lr": 0.003,
    "eval_every": 250,
    "seed": 0,
    "mamba_state": 64,
    "mamba_head_dim": 48,
    "m2rnn_head_dim": 50,
    "gdn2_head_dim": 28,
    "gdn2_repo": null,
    "device": "cuda",
    "out": "results/enwik8/transformer_s0.json"
  },
  "params": 361088,
  "final_val_bpc": 2.486075925992602,
  "history": [
    {
      "step": 250,
      "train_bpc": 3.640404925955312,
      "val_bpc": 3.611160566045973
    },
    {
      "step": 500,
      "train_bpc": 3.1314752413832956,
      "val_bpc": 3.111429029590052
    },
    {
      "step": 750,
      "train_bpc": 2.9079287521387998,
      "val_bpc": 2.851796388117424
    },
    {
      "step": 1000,
      "train_bpc": 2.7388952597729865,
      "val_bpc": 2.6402073796351293
    },
    {
      "step": 1250,
      "train_bpc": 2.7071240447658456,
      "val_bpc": 2.564150137580694
    },
    {
      "step": 1500,
      "train_bpc": 2.2161103088821603,
      "val_bpc": 2.486075925992602
    }
  ],
  "wall_sec": 9.6
}